propertylistings/__init__.py
propertylistings/archive.py
propertylistings/properties_scraper.py
propertylistings/resources.py
propertylistings/utilities.py
propertylistings/scripts/__init__.py
propertylistings/scripts/propertylistings.py
propertylistings-0.1.0.dist-info/LICENSE
propertylistings-0.1.0.dist-info/METADATA
propertylistings-0.1.0.dist-info/WHEEL
propertylistings-0.1.0.dist-info/entry_points.txt
propertylistings-0.1.0.dist-info/top_level.txt
propertylistings-0.1.0.dist-info/RECORD
