Metadata-Version: 2.1
Name: propertylistings
Version: 0.1.0
Summary: Webscraping tool for archiving sales records on RightMove.
Home-page: https://github.com/christopher-christofi/propertylistings
Author: Christopher Christofi
Author-email: christopherlchristofi@outlook.com
License: GPL-3.0
Project-URL: Bug Tracker, https://github.com/christopher-christofi/propertylistings/issues
Platform: UNKNOWN
Classifier: License :: OSI Approved :: GNU General Public License v3 (GPLv3)
Classifier: Operating System :: OS Independent
Classifier: Programming Language :: Python :: 3
Requires-Python: >=3.0
License-File: LICENSE
Requires-Dist: beautifulsoup4
Requires-Dist: requests
Requires-Dist: click
